deepoc/__init__.py
deepoc/classifier/__init__.py
deepoc/classifier/classifier_service.py
deepoc/dataset/__init__.py
deepoc/dataset/dataset_builder.py
deepoc/dataset/feature_builder.py
deepoc/ontology/__init__.py
deepoc/ontology/gene_ontology_service.py
deepoc/ontology/ontology_service.py
deepoc/similarity/__init__.py
deepoc/similarity/similarity_service.py
tests/__init__.py
tests/test_dataset_generation.py
tests/test_dnn_training.py
tests/test_feature_generator.py
tests/test_prediction.py
deepoc-1.1.4.dist-info/LICENSE
deepoc-1.1.4.dist-info/METADATA
deepoc-1.1.4.dist-info/WHEEL
deepoc-1.1.4.dist-info/top_level.txt
deepoc-1.1.4.dist-info/RECORD
