Metadata-Version: 2.1
Name: deepoc
Version: 1.1.4
Summary: A machine learning tool to classify complex datasets based on ontologies
Home-page: https://bitbucket.org/biomodels/deepoc
Author: Tu Vu
Author-email: tvu@ebi.ac.uk
License: UNKNOWN
Platform: UNKNOWN
Classifier: Programming Language :: Python :: 3
Classifier: License :: OSI Approved :: GNU Affero General Public License v3
Classifier: Operating System :: OS Independent
Requires-Dist: tensorflow
Requires-Dist: obonet
Requires-Dist: networkx
